{"gradients/global_encoder.transformer_encoder.layers.5.self_attn.out_proj.weight":{"_type":"histogram","values":[65536],"bins":[0,0]},"_wandb":{"runtime":183},"gradients/hierarchical_encoder.temporal_attentions.2.in_proj_bias":{"_type":"histogram","values":[768],"bins":[0,0]},"gradients/global_encoder.transformer_encoder.layers.2.norm2.bias":{"values":[256],"bins":[0,0],"_type":"histogram"},"gradients/global_encoder.transformer_encoder.layers.2.self_attn.in_proj_bias":{"_type":"histogram","values":[768],"bins":[0,0]},"gradients/global_encoder.transformer_encoder.layers.1.linear1.bias":{"_type":"histogram","values":[1024],"bins":[0,0]},"gradients/global_encoder.transformer_encoder.layers.5.norm1.bias":{"_type":"histogram","values":[256],"bins":[0,0]},"gradients/body_encoder.input_projection.1.weight":{"_type":"histogram","values":[256],"bins":[0,0]},"gradients/classifier.classifier.1.bias":{"_type":"histogram","values":[256],"bins":[0,0]},"gradients/hierarchical_encoder.temporal_attentions.1.in_proj_bias":{"values":[768],"bins":[0,0],"_type":"histogram"},"gradients/global_encoder.transformer_encoder.layers.1.self_attn.out_proj.weight":{"values":[65536],"bins":[0,0],"_type":"histogram"},"test/accuracy":0.01282051282051282,"gradients/classifier.classifier.0.weight":{"bins":[0,0],"_type":"histogram","values":[256]},"learning_rate":0.0008869817936485216,"gradients/global_encoder.transformer_encoder.layers.3.linear2.bias":{"_type":"histogram","values":[256],"bins":[0,0]},"gradients/global_encoder.transformer_encoder.layers.4.self_attn.out_proj.weight":{"bins":[0,0],"_type":"histogram","values":[65536]},"gradients/cross_stream_fusion.fusion_proj.0.bias":{"values":[256],"bins":[0,0],"_type":"histogram"},"gradients/body_encoder.input_projection.0.weight":{"bins":[0,0],"_type":"histogram","values":[25344]},"val/loss":7.158482477262423,"gradients/cross_stream_fusion.cross_attentions.0.out_proj.bias":{"bins":[0,0],"_type":"histogram","values":[256]},"gradients/global_encoder.transformer_encoder.layers.4.norm2.weight":{"_type":"histogram","values":[256],"bins":[0,0]},"gradients/global_encoder.transformer_encoder.layers.3.linear1.bias":{"bins":[0,0],"_type":"histogram","values":[1024]},"gradients/classifier.classifier.1.weight":{"bins":[0,0],"_type":"histogram","values":[65536]},"gradients/body_encoder.input_projection.1.bias":{"values":[256],"bins":[0,0],"_type":"histogram"},"eval/confusion_matrix":{"path":"media/images/eval/confusion_matrix_137_b561fd0d8d02466de468.png","format":"png","width":3286,"height":2984,"_type":"image-file","sha256":"b561fd0d8d02466de468861238c6ac7e9672010932bfbb9349d77f3df496abf1","size":84409},"gradients/global_encoder.transformer_encoder.layers.3.self_attn.in_proj_weight":{"_type":"histogram","values":[196608],"bins":[0,0]},"gradients/global_encoder.transformer_encoder.layers.1.norm1.weight":{"_type":"histogram","values":[256],"bins":[0,0]},"gradients/global_encoder.transformer_encoder.layers.1.linear1.weight":{"_type":"histogram","values":[262144],"bins":[0,0]},"gradients/body_encoder.temporal_convs.1.conv.bias":{"bins":[0,0],"_type":"histogram","values":[256]},"gradients/global_encoder.transformer_encoder.layers.2.linear2.weight":{"values":[262144],"bins":[0,0],"_type":"histogram"},"gradients/global_encoder.transformer_encoder.layers.0.linear1.bias":{"bins":[0,0],"_type":"histogram","values":[1024]},"gradients/global_encoder.transformer_encoder.layers.5.norm2.bias":{"bins":[0,0],"_type":"histogram","values":[256]},"gradients/body_encoder.temporal_convs.0.norm.bias":{"values":[256],"bins":[0,0],"_type":"histogram"},"gradients/hierarchical_encoder.temporal_attentions.0.in_proj_bias":{"_type":"histogram","values":[768],"bins":[0,0]},"gradients/cross_stream_fusion.fusion_proj.0.weight":{"_type":"histogram","values":[65536],"bins":[0,0]},"gradients/global_encoder.transformer_encoder.layers.5.linear1.weight":{"_type":"histogram","values":[262144],"bins":[0,0]},"gradients/global_encoder.transformer_encoder.layers.3.norm1.weight":{"bins":[0,0],"_type":"histogram","values":[256]},"gradients/global_encoder.transformer_encoder.layers.0.norm1.bias":{"bins":[0,0],"_type":"histogram","values":[256]},"gradients/cross_stream_fusion.cross_attentions.0.in_proj_bias":{"bins":[0,0],"_type":"histogram","values":[768]},"train/batch_loss":8.859883308410645,"test/f1_score":0.0006027727546714888,"gradients/body_encoder.spatial_attention.norm.weight":{"_type":"histogram","values":[256],"bins":[0,0]},"gradients/global_encoder.transformer_encoder.layers.5.linear1.bias":{"_type":"histogram","values":[1024],"bins":[0,0]},"gradients/global_encoder.transformer_encoder.layers.0.linear2.bias":{"values":[256],"bins":[0,0],"_type":"histogram"},"gradients/global_encoder.transformer_encoder.layers.4.self_attn.in_proj_bias":{"_type":"histogram","values":[768],"bins":[0,0]},"gradients/global_encoder.transformer_encoder.layers.2.self_attn.out_proj.weight":{"_type":"histogram","values":[65536],"bins":[0,0]},"gradients/global_encoder.transformer_encoder.layers.4.norm1.bias":{"bins":[0,0],"_type":"histogram","values":[256]},"gradients/global_encoder.transformer_encoder.layers.3.linear1.weight":{"bins":[0,0],"_type":"histogram","values":[262144]},"train/loss":8.930766695424131,"gradients/global_encoder.transformer_encoder.layers.2.norm1.bias":{"bins":[0,0],"_type":"histogram","values":[256]},"gradients/body_encoder.temporal_convs.1.conv.weight":{"bins":[0,0],"_type":"histogram","values":[196608]},"eval/top_k_accuracy":{"format":"png","width":1182,"height":730,"_type":"image-file","sha256":"2ff50b4f8e868fdd5b32515666aeb45bcae53525f4b4d6dc352053bc14944801","size":29288,"path":"media/images/eval/top_k_accuracy_140_2ff50b4f8e868fdd5b32.png"},"gradients/global_encoder.transformer_encoder.layers.4.linear1.weight":{"values":[262144],"bins":[0,0],"_type":"histogram"},"gradients/hierarchical_encoder.scale_fusion.0.weight":{"_type":"histogram","values":[196608],"bins":[0,0]},"gradients/global_encoder.transformer_encoder.layers.4.norm2.bias":{"bins":[0,0],"_type":"histogram","values":[256]},"_timestamp":1.769817910888198e+09,"gradients/body_encoder.temporal_convs.1.norm.bias":{"_type":"histogram","values":[256],"bins":[0,0]},"test/precision":0.00030525030525030525,"gradients/global_encoder.transformer_encoder.layers.2.self_attn.in_proj_weight":{"_type":"histogram","values":[196608],"bins":[0,0]},"gradients/classifier.classifier.4.weight":{"values":[32768],"bins":[0,0],"_type":"histogram"},"gradients/hierarchical_encoder.temporal_attentions.0.out_proj.bias":{"values":[256],"bins":[0,0],"_type":"histogram"},"gradients/global_encoder.transformer_encoder.layers.1.norm2.weight":{"bins":[0,0],"_type":"histogram","values":[256]},"gradients/classifier.classifier.7.weight":{"_type":"histogram","values":[7040],"bins":[0,0]},"gradients/body_encoder.spatial_attention.attention.in_proj_weight":{"values":[196608],"bins":[0,0],"_type":"histogram"},"gradients/global_encoder.transformer_encoder.layers.2.norm2.weight":{"bins":[0,0],"_type":"histogram","values":[256]},"eval/per_class_accuracy":{"sha256":"057717acf309672ef674c351f571b591bc1de66e9ba9520c95d8fa283dc72c66","size":60192,"path":"media/images/eval/per_class_accuracy_139_057717acf309672ef674.png","format":"png","width":2385,"height":883,"_type":"image-file"},"gradients/global_encoder.transformer_encoder.layers.5.linear2.bias":{"_type":"histogram","values":[256],"bins":[0,0]},"gradients/global_encoder.transformer_encoder.layers.4.self_attn.in_proj_weight":{"values":[196608],"bins":[0,0],"_type":"histogram"},"gradients/global_encoder.norm.weight":{"values":[256],"bins":[0,0],"_type":"histogram"},"gradients/global_encoder.transformer_encoder.layers.0.linear1.weight":{"_type":"histogram","values":[262144],"bins":[0,0]},"gradients/global_encoder.transformer_encoder.layers.1.self_attn.in_proj_weight":{"_type":"histogram","values":[196608],"bins":[0,0]},"gradients/cross_stream_fusion.fusion_proj.1.weight":{"bins":[0,0],"_type":"histogram","values":[256]},"gradients/hierarchical_encoder.temporal_attentions.2.in_proj_weight":{"bins":[0,0],"_type":"histogram","values":[196608]},"gradients/body_encoder.temporal_convs.0.conv.bias":{"_type":"histogram","values":[256],"bins":[0,0]},"gradients/hierarchical_encoder.temporal_attentions.0.out_proj.weight":{"values":[65536],"bins":[0,0],"_type":"histogram"},"train/batch":35,"gradients/global_encoder.transformer_encoder.layers.2.linear1.weight":{"_type":"histogram","values":[262144],"bins":[0,0]},"gradients/global_encoder.transformer_encoder.layers.2.linear2.bias":{"_type":"histogram","values":[256],"bins":[0,0]},"gradients/cross_stream_fusion.norm.weight":{"_type":"histogram","values":[256],"bins":[0,0]},"gradients/global_encoder.transformer_encoder.layers.0.norm1.weight":{"values":[256],"bins":[0,0],"_type":"histogram"},"gradients/global_encoder.transformer_encoder.layers.0.self_attn.out_proj.weight":{"values":[65536],"bins":[0,0],"_type":"histogram"},"gradients/global_encoder.transformer_encoder.layers.5.self_attn.in_proj_weight":{"bins":[0,0],"_type":"histogram","values":[196608]},"gradients/body_encoder.spatial_attention.attention.out_proj.bias":{"_type":"histogram","values":[256],"bins":[0,0]},"gradients/global_encoder.transformer_encoder.layers.3.self_attn.in_proj_bias":{"_type":"histogram","values":[768],"bins":[0,0]},"gradients/global_encoder.norm.bias":{"values":[256],"bins":[0,0],"_type":"histogram"},"gradients/global_encoder.transformer_encoder.layers.1.self_attn.out_proj.bias":{"bins":[0,0],"_type":"histogram","values":[256]},"gradients/global_encoder.transformer_encoder.layers.4.linear2.weight":{"bins":[0,0],"_type":"histogram","values":[262144]},"gradients/hierarchical_encoder.temporal_attentions.1.out_proj.bias":{"bins":[0,0],"_type":"histogram","values":[256]},"gradients/hierarchical_encoder.temporal_attentions.1.in_proj_weight":{"_type":"histogram","values":[196608],"bins":[0,0]},"train/batch_accuracy":0,"gradients/body_encoder.input_projection.0.bias":{"values":[256],"bins":[0,0],"_type":"histogram"},"gradients/class_token":{"_type":"histogram","values":[256],"bins":[0,0]},"gradients/global_encoder.transformer_encoder.layers.5.norm1.weight":{"values":[256],"bins":[0,0],"_type":"histogram"},"gradients/global_encoder.transformer_encoder.layers.3.norm1.bias":{"bins":[0,0],"_type":"histogram","values":[256]},"gradients/global_encoder.transformer_encoder.layers.5.self_attn.in_proj_bias":{"values":[768],"bins":[0,0],"_type":"histogram"},"gradients/global_encoder.transformer_encoder.layers.2.norm1.weight":{"bins":[0,0],"_type":"histogram","values":[256]},"test/top5_accuracy":0.02564102564102564,"_runtime":183,"gradients/global_encoder.transformer_encoder.layers.3.self_attn.out_proj.bias":{"_type":"histogram","values":[256],"bins":[0,0]},"model/total_parameters":6847543,"gradients/global_encoder.transformer_encoder.layers.4.norm1.weight":{"bins":[0,0],"_type":"histogram","values":[256]},"gradients/hierarchical_encoder.temporal_attentions.2.out_proj.weight":{"_type":"histogram","values":[65536],"bins":[0,0]},"epoch":17,"eval/per_signer_accuracy":{"size":31821,"path":"media/images/eval/per_signer_accuracy_138_6b53d3b5b71f78c1a522.png","format":"png","width":1482,"height":880,"_type":"image-file","sha256":"6b53d3b5b71f78c1a5223f322ab53743ea55c8e2bbeead5d95276625dc3597c4"},"gradients/global_encoder.transformer_encoder.layers.1.norm1.bias":{"bins":[0,0],"_type":"histogram","values":[256]},"gradients/classifier.classifier.0.bias":{"values":[256],"bins":[0,0],"_type":"histogram"},"gradients/hierarchical_encoder.scale_fusion.1.weight":{"_type":"histogram","values":[256],"bins":[0,0]},"gradients/global_encoder.transformer_encoder.layers.2.linear1.bias":{"values":[1024],"bins":[0,0],"_type":"histogram"},"train/accuracy":0.019736842105263157,"gradients/global_encoder.transformer_encoder.layers.3.norm2.weight":{"values":[256],"bins":[0,0],"_type":"histogram"},"gradients/classifier.classifier.4.bias":{"bins":[0,0],"_type":"histogram","values":[128]},"gradients/global_encoder.transformer_encoder.layers.2.self_attn.out_proj.bias":{"values":[256],"bins":[0,0],"_type":"histogram"},"gradients/body_encoder.temporal_convs.1.norm.weight":{"_type":"histogram","values":[256],"bins":[0,0]},"gradients/cross_stream_fusion.norm.bias":{"bins":[0,0],"_type":"histogram","values":[256]},"gradients/global_encoder.transformer_encoder.layers.5.self_attn.out_proj.bias":{"values":[256],"bins":[0,0],"_type":"histogram"},"_step":141,"gradients/hierarchical_encoder.temporal_attentions.2.out_proj.bias":{"bins":[0,0],"_type":"histogram","values":[256]},"gradients/global_encoder.transformer_encoder.layers.4.linear1.bias":{"bins":[0,0],"_type":"histogram","values":[1024]},"gradients/body_encoder.temporal_convs.0.norm.weight":{"bins":[0,0],"_type":"histogram","values":[256]},"gradients/global_encoder.transformer_encoder.layers.0.self_attn.in_proj_bias":{"_type":"histogram","values":[768],"bins":[0,0]},"gradients/cross_stream_fusion.cross_attentions.0.in_proj_weight":{"values":[196608],"bins":[0,0],"_type":"histogram"},"gradients/global_encoder.transformer_encoder.layers.0.self_attn.in_proj_weight":{"values":[196608],"bins":[0,0],"_type":"histogram"},"gradients/hierarchical_encoder.temporal_attentions.1.out_proj.weight":{"_type":"histogram","values":[65536],"bins":[0,0]},"gradients/global_encoder.transformer_encoder.layers.1.self_attn.in_proj_bias":{"bins":[0,0],"_type":"histogram","values":[768]},"gradients/global_encoder.transformer_encoder.layers.4.self_attn.out_proj.bias":{"bins":[0,0],"_type":"histogram","values":[256]},"val/accuracy":0.025974025974025976,"gradients/global_encoder.transformer_encoder.layers.1.norm2.bias":{"bins":[0,0],"_type":"histogram","values":[256]},"gradients/hierarchical_encoder.temporal_attentions.0.in_proj_weight":{"_type":"histogram","values":[196608],"bins":[0,0]},"gradients/global_encoder.transformer_encoder.layers.0.self_attn.out_proj.bias":{"values":[256],"bins":[0,0],"_type":"histogram"},"gradients/classifier.classifier.7.bias":{"_type":"histogram","values":[55],"bins":[0,0]},"gradients/global_encoder.transformer_encoder.layers.3.self_attn.out_proj.weight":{"bins":[0,0],"_type":"histogram","values":[65536]},"gradients/global_encoder.transformer_encoder.layers.0.norm2.weight":{"_type":"histogram","values":[256],"bins":[0,0]},"gradients/global_encoder.transformer_encoder.layers.1.linear2.bias":{"bins":[0,0],"_type":"histogram","values":[256]},"gradients/body_encoder.temporal_convs.0.conv.weight":{"values":[196608],"bins":[0,0],"_type":"histogram"},"gradients/global_encoder.transformer_encoder.layers.4.linear2.bias":{"bins":[0,0],"_type":"histogram","values":[256]},"gradients/hierarchical_encoder.norm.bias":{"_type":"histogram","values":[256],"bins":[0,0]},"test/recall":0.023809523809523808,"gradients/global_encoder.transformer_encoder.layers.5.linear2.weight":{"bins":[0,0],"_type":"histogram","values":[262144]},"gradients/global_encoder.transformer_encoder.layers.0.linear2.weight":{"_type":"histogram","values":[262144],"bins":[0,0]},"gradients/hierarchical_encoder.scale_fusion.0.bias":{"bins":[0,0],"_type":"histogram","values":[256]},"gradients/hierarchical_encoder.scale_fusion.1.bias":{"_type":"histogram","values":[256],"bins":[0,0]},"gradients/global_encoder.transformer_encoder.layers.3.linear2.weight":{"values":[262144],"bins":[0,0],"_type":"histogram"},"gradients/cross_stream_fusion.fusion_proj.1.bias":{"_type":"histogram","values":[256],"bins":[0,0]},"gradients/body_encoder.spatial_attention.attention.in_proj_bias":{"_type":"histogram","values":[768],"bins":[0,0]},"gradients/global_encoder.transformer_encoder.layers.0.norm2.bias":{"values":[256],"bins":[0,0],"_type":"histogram"},"gradients/global_encoder.transformer_encoder.layers.3.norm2.bias":{"values":[256],"bins":[0,0],"_type":"histogram"},"gradients/global_encoder.transformer_encoder.layers.5.norm2.weight":{"bins":[0,0],"_type":"histogram","values":[256]},"gradients/body_encoder.spatial_attention.attention.out_proj.weight":{"_type":"histogram","values":[65536],"bins":[0,0]},"gradients/body_encoder.spatial_attention.norm.bias":{"_type":"histogram","values":[256],"bins":[0,0]},"eval/confusion_matrix_normalized":{"path":"media/images/eval/confusion_matrix_normalized_137_82f82fb330b2aab19f90.png","format":"png","width":3286,"height":2984,"_type":"image-file","sha256":"82f82fb330b2aab19f9015a839917eb48f92d8f0ec0daea30c03a65d642a3917","size":83255},"gradients/cross_stream_fusion.cross_attentions.0.out_proj.weight":{"_type":"histogram","values":[65536],"bins":[0,0]},"gradients/global_encoder.transformer_encoder.layers.1.linear2.weight":{"_type":"histogram","values":[262144],"bins":[0,0]},"gradients/hierarchical_encoder.norm.weight":{"bins":[0,0],"_type":"histogram","values":[256]}}